AUTHORS
CHANGES.rst
LICENSE
MANIFEST.in
README.rst
setup.py
bowerrecipe/__init__.py
bowerrecipe.egg-info/PKG-INFO
bowerrecipe.egg-info/SOURCES.txt
bowerrecipe.egg-info/dependency_links.txt
bowerrecipe.egg-info/entry_points.txt
bowerrecipe.egg-info/not-zip-safe
bowerrecipe.egg-info/requires.txt
bowerrecipe.egg-info/top_level.txt
bowerrecipe/tests/__init__.py
bowerrecipe/tests/tests.py