Metadata-Version: 1.1
Name: bowerrecipe
Version: 0.1.1
Summary: zc.buildout recipe to install static resources using Twitter Bower.
Home-page: http://github.com/anshumanb/bowerrecipe
Author: Anshuman Bhaduri
Author-email: anshuman.bhaduri0@gmail.com
License: MIT
Platform: UNKNOWN
Classifier: Framework :: Buildout
Classifier: Framework :: Buildout :: Recipe
Classifier: License :: OSI Approved :: MIT License
Classifier: Development Status :: 4 - Beta
Classifier: Operating System :: OS Independent
Classifier: Intended Audience :: Developers
Classifier: Topic :: Software Development :: Build Tools
